Metadata-Version: 2.1
Name: msdss-base-database
Version: 0.1.1
Summary: Base database for the Modular Spatial Decision Support Systems (MSDSS) framework
Home-page: https://github.com/rrwen/msdss-base-database
Author: Richard Wen
Author-email: rrwen.dev@gmail.com
License: UNKNOWN
Project-URL: Bug Tracker, https://github.com/rrwen/msdss-base-database/issues
Platform: UNKNOWN
Classifier: Programming Language :: Python :: 3
Classifier: License :: OSI Approved :: MIT License
Classifier: Operating System :: OS Independent
Requires-Python: >=3.8
Provides-Extra: postgresql
Provides-Extra: mysql
Provides-Extra: sqlite
License-File: LICENSE
